pydantictypes/__init__.py
pydantictypes/_validation_utils.py
pydantictypes/abstract_string_to_int.py
pydantictypes/abstract_string_to_optional_int.py
pydantictypes/empty_string_to_none.py
pydantictypes/half_width_string.py
pydantictypes/kanji_yen_string_to_int.py
pydantictypes/py.typed
pydantictypes/string_to_datetime.py
pydantictypes/string_to_optional_bool.py
pydantictypes/string_to_optional_int.py
pydantictypes/string_to_optional_str.py
pydantictypes/string_with_comma_to_int.py
pydantictypes/string_with_comma_to_optional_int.py
pydantictypes/string_with_length_constraint.py
pydantictypes/symbol_yen_string_to_int.py
pydantictypes/utility.py
pydantictypes/validators.py
pydantictypes-1.2.1.dist-info/licenses/LICENSE
pydantictypes-1.2.1.dist-info/METADATA
pydantictypes-1.2.1.dist-info/WHEEL
pydantictypes-1.2.1.dist-info/top_level.txt
pydantictypes-1.2.1.dist-info/RECORD
