Metadata-Version: 2.4
Name: pydantictypes
Version: 1.2.1
Summary: Common used type definitions with Pydantic.
Author-email: Yukihiko Shinoda <yuk.hik.future@gmail.com>
Maintainer-email: Yukihiko Shinoda <yuk.hik.future@gmail.com>
License: MIT License
Project-URL: homepage, https://github.com/yukihiko-shinoda/pydantic-types
Project-URL: repository, https://github.com/yukihiko-shinoda/pydantic-types
Keywords: pydantictypes
Classifier: Development Status :: 4 - Beta
Classifier: Framework :: Pydantic
Classifier: Framework :: Pydantic :: 2
Classifier: Intended Audience :: Developers
Classifier: Intended Audience :: Financial and Insurance Industry
Classifier: Intended Audience :: Information Technology
Classifier: License :: OSI Approved :: MIT License
Classifier: Natural Language :: English
Classifier: Operating System :: OS Independent
Classifier: Programming Language :: Python
Classifier: Programming Language :: Python :: 3
Classifier: Programming Language :: Python :: 3.7
Classifier: Programming Language :: Python :: 3.8
Classifier: Programming Language :: Python :: 3.9
Classifier: Programming Language :: Python :: 3.10
Classifier: Programming Language :: Python :: 3.11
Classifier: Programming Language :: Python :: 3.12
Classifier: Programming Language :: Python :: 3.13
Classifier: Topic :: Software Development
Classifier: Topic :: Software Development :: Libraries
Classifier: Topic :: Software Development :: Libraries :: Python Modules
Classifier: Topic :: Text Processing
Classifier: Typing :: Typed
Requires-Python: >=3.7
License-File: LICENSE
Requires-Dist: pydantic>=2.0.0
Requires-Dist: typing_extensions; python_version < "3.11"
Dynamic: license-file
